{"cameraMode":{"drawMode":0,"name":"Shaded","section":"Shading Mode"},"sceneLighting":false,"audioPlay":false,"sceneViewState":{"m_AlwaysRefresh":false,"showFog":true,"showSkybox":false,"showFlares":true,"showImageEffects":true,"showParticleSystems":true,"showVisualEffectGraphs":true,"m_FxEnabled":true},"in2DMode":false,"pivot":{"x":0.0,"y":0.7557377219200134,"z":-0.08181247115135193},"rotation":{"x":0.09816981852054596,"y":-0.897625744342804,"z":0.2545337975025177,"w":0.34620216488838198},"size":2.3285415172576906,"orthographic":false}